litl/__init__.py
litl/cli.py
litl/datawrapper.py
litl/dot_litl.py
litl/evaluator.py
litl/run.py
litl/blobs/__init__.py
litl/blobs/array_blob.py
litl/blobs/blob.py
litl/blobs/bytes_blob.py
litl/blobs/model_blob.py
litl/compressors/__init__.py
litl/compressors/compressor.py
litl/compressors/compressor_about.py
litl-0.1.3.dist-info/METADATA
litl-0.1.3.dist-info/WHEEL
litl-0.1.3.dist-info/entry_points.txt
litl-0.1.3.dist-info/licenses/LICENSE
litl-0.1.3.dist-info/RECORD
