Metadata-Version: 2.4
Name: litl
Version: 0.1.3
Summary: Lightweight InTerface for Lossy compression
Project-URL: Homepage, https://github.com/GulkoA/litl
Author-email: Alex Gulko <alex@gulko.net>
License-Expression: MIT
License-File: LICENSE
Classifier: Operating System :: OS Independent
Classifier: Programming Language :: Python :: 3
Requires-Python: >=3.8
Requires-Dist: numpy
Requires-Dist: pydantic
Requires-Dist: pytorch-msssim
Requires-Dist: rich
Requires-Dist: torch
Requires-Dist: torcheval
Requires-Dist: zstd
Provides-Extra: netcdf
Requires-Dist: netcdf4; extra == 'netcdf'
